gtrends_api/__init__.py
gtrends_api/main.py
gtrends_api/dependencies/__init__.py
gtrends_api/dependencies/core.py
gtrends_api/middleware/__init__.py
gtrends_api/middleware/cors.py
gtrends_api/middleware/error_handling.py
gtrends_api/middleware/rate_limiting.py
gtrends_api/routers/__init__.py
gtrends_api/routers/comparison.py
gtrends_api/routers/geo.py
gtrends_api/routers/growth.py
gtrends_api/routers/opportunities.py
gtrends_api/routers/related.py
gtrends_api/routers/suggestions.py
gtrends_api/routers/trending.py
gtrends_api/schemas/__init__.py
gtrends_api/schemas/requests.py
gtrends_api/schemas/responses.py
gtrends_cli/__init__.py
gtrends_cli/main.py
gtrends_cli/commands/__init__.py
gtrends_cli/commands/categories_command.py
gtrends_cli/commands/compare_command.py
gtrends_cli/commands/geo_command.py
gtrends_cli/commands/growth_command.py
gtrends_cli/commands/help_command.py
gtrends_cli/commands/opportunities_command.py
gtrends_cli/commands/related_command.py
gtrends_cli/commands/suggestions_command.py
gtrends_cli/commands/trending_command.py
gtrends_cli/formatters/__init__.py
gtrends_cli/formatters/console.py
gtrends_cli/formatters/export.py
gtrends_cli-0.3.5.dist-info/licenses/LICENSE
gtrends_core/__init__.py
gtrends_core/config.py
gtrends_core/exceptions/__init__.py
gtrends_core/exceptions/trends_exceptions.py
gtrends_core/exceptions/trends_exceptions.py.bak
gtrends_core/models/__init__.py
gtrends_core/models/base.py
gtrends_core/models/comparison.py
gtrends_core/models/related.py
gtrends_core/models/trending.py
gtrends_core/services/__init__.py
gtrends_core/services/comparison_service.py
gtrends_core/services/geo_service.py
gtrends_core/services/growth_service.py
gtrends_core/services/opportunity_service.py
gtrends_core/services/related_service.py
gtrends_core/services/suggestion_service.py
gtrends_core/services/trending_service.py
gtrends_core/utils/__init__.py
gtrends_core/utils/formatters.py
gtrends_core/utils/helpers.py
gtrends_core/utils/validators.py
gtrends_cli-0.3.5.dist-info/METADATA
gtrends_cli-0.3.5.dist-info/WHEEL
gtrends_cli-0.3.5.dist-info/entry_points.txt
gtrends_cli-0.3.5.dist-info/top_level.txt
gtrends_cli-0.3.5.dist-info/RECORD
