Metadata-Version: 2.4
Name: gtrends-cli
Version: 0.3.5
Summary: CLI and API tools for Google Trends data analysis and content suggestions
Home-page: https://github.com/Nao-30/google-trends-cli
Author: Mohammed A. Al-Kebsi
Author-email: "Mohammed A. Al-Kebsi" <mohammed.k@mohammed-alkebsi.dev>
License: MIT
Project-URL: Homepage, https://github.com/Nao-30/google-trends-cli
Project-URL: Documentation, https://github.com/Nao-30/google-trends-cli/tree/main/docs
Project-URL: Repository, https://github.com/Nao-30/google-trends-cli.git
Project-URL: Issues, https://github.com/Nao-30/google-trends-cli/issues
Project-URL: Changelog, https://github.com/Nao-30/google-trends-cli/blob/main/CHANGELOG.md
Project-URL: MyBlog, https://blog.mohammed-alkebsi.dev
Project-URL: Download Link, https://github.com/Nao-30/google-trends-cli/archive/refs/tags/v0.3.5.tar.gz
Platform: unix
Platform: linux
Platform: osx
Platform: win32
Classifier: Programming Language :: Python :: 3
Classifier: Programming Language :: Python :: 3.9
Classifier: Programming Language :: Python :: 3.10
Classifier: Programming Language :: Python :: 3.12
Classifier: License :: OSI Approved :: MIT License
Classifier: Operating System :: OS Independent
Classifier: Development Status :: 4 - Beta
Classifier: Intended Audience :: Developers
Classifier: Intended Audience :: Information Technology
Classifier: Intended Audience :: Science/Research
Classifier: Topic :: Internet :: WWW/HTTP :: Indexing/Search
Classifier: Topic :: Scientific/Engineering :: Information Analysis
Classifier: Topic :: Software Development :: Libraries :: Python Modules
Requires-Python: >=3.9
License-File: LICENSE
Dynamic: author
Dynamic: home-page
Dynamic: license-file
Dynamic: requires-python
